[{"variables":[{"defaultValue":"","dataType":"date/time","name":"$s_Site_Hours_Day_Pre_DC.StartTime","description":"The time this task started"},{"defaultValue":"","dataType":"date/time","name":"$s_Site_Hours_Day_Pre_DC.EndTime","description":"The time this task completed"},{"defaultValue":"","dataType":"integer","name":"$s_Site_Hours_Day_Pre_DC.Status","description":"Status of this task's execution"},{"defaultValue":"","dataType":"integer","name":"$s_Site_Hours_Day_Pre_DC.PrevTaskStatus","description":"Status of the previous task that is not disabled"},{"defaultValue":"","dataType":"integer","name":"$s_Site_Hours_Day_Pre_DC.ErrorCode","description":"Error code for this task's execution"},{"defaultValue":"","dataType":"string","name":"$s_Site_Hours_Day_Pre_DC.ErrorMsg","description":"Error message for this task's execution"},{"defaultValue":"","dataType":"bigint","name":"$s_Site_Hours_Day_Pre_DC.SrcSuccessRows","description":"Rows successfully read"},{"defaultValue":"","dataType":"bigint","name":"$s_Site_Hours_Day_Pre_DC.SrcFailedRows","description":"Rows failed to read"},{"defaultValue":"","dataType":"bigint","name":"$s_Site_Hours_Day_Pre_DC.TgtSuccessRows","description":"Rows successfully loaded"},{"defaultValue":"","dataType":"bigint","name":"$s_Site_Hours_Day_Pre_DC.TgtFailedRows","description":"Rows failed to load"},{"defaultValue":"","dataType":"integer","name":"$s_Site_Hours_Day_Pre_DC.TotalTransErrors","description":"Total number of transformation errors"},{"defaultValue":"","dataType":"integer","name":"$s_Site_Hours_Day_Pre_DC.FirstErrorCode","description":"First error code"},{"defaultValue":"","dataType":"string","name":"$s_Site_Hours_Day_Pre_DC.FirstErrorMsg","description":"First error message"},{"defaultValue":"","dataType":"date/time","name":"$s_Site_Hours_Day.StartTime","description":"The time this task started"},{"defaultValue":"","dataType":"date/time","name":"$s_Site_Hours_Day.EndTime","description":"The time this task completed"},{"defaultValue":"","dataType":"integer","name":"$s_Site_Hours_Day.Status","description":"Status of this task's execution"},{"defaultValue":"","dataType":"integer","name":"$s_Site_Hours_Day.PrevTaskStatus","description":"Status of the previous task that is not disabled"},{"defaultValue":"","dataType":"integer","name":"$s_Site_Hours_Day.ErrorCode","description":"Error code for this task's execution"},{"defaultValue":"","dataType":"string","name":"$s_Site_Hours_Day.ErrorMsg","description":"Error message for this task's execution"},{"defaultValue":"","dataType":"bigint","name":"$s_Site_Hours_Day.SrcSuccessRows","description":"Rows successfully read"},{"defaultValue":"","dataType":"bigint","name":"$s_Site_Hours_Day.SrcFailedRows","description":"Rows failed to read"},{"defaultValue":"","dataType":"bigint","name":"$s_Site_Hours_Day.TgtSuccessRows","description":"Rows successfully loaded"},{"defaultValue":"","dataType":"bigint","name":"$s_Site_Hours_Day.TgtFailedRows","description":"Rows failed to load"},{"defaultValue":"","dataType":"integer","name":"$s_Site_Hours_Day.TotalTransErrors","description":"Total number of transformation errors"},{"defaultValue":"","dataType":"integer","name":"$s_Site_Hours_Day.FirstErrorCode","description":"First error code"},{"defaultValue":"","dataType":"string","name":"$s_Site_Hours_Day.FirstErrorMsg","description":"First error message"},{"defaultValue":"","dataType":"date/time","name":"$Start.StartTime","description":"The time this task started"},{"defaultValue":"","dataType":"date/time","name":"$Start.EndTime","description":"The time this task completed"},{"defaultValue":"","dataType":"integer","name":"$Start.Status","description":"Status of this task's execution"},{"defaultValue":"","dataType":"integer","name":"$Start.PrevTaskStatus","description":"Status of the previous task that is not disabled"},{"defaultValue":"","dataType":"integer","name":"$Start.ErrorCode","description":"Error code for this task's execution"},{"defaultValue":"","dataType":"string","name":"$Start.ErrorMsg","description":"Error message for this task's execution"},{"defaultValue":"","dataType":"date/time","name":"$s_Site_Hours_Day_Pre_Store.StartTime","description":"The time this task started"},{"defaultValue":"","dataType":"date/time","name":"$s_Site_Hours_Day_Pre_Store.EndTime","description":"The time this task completed"},{"defaultValue":"","dataType":"integer","name":"$s_Site_Hours_Day_Pre_Store.Status","description":"Status of this task's execution"},{"defaultValue":"","dataType":"integer","name":"$s_Site_Hours_Day_Pre_Store.PrevTaskStatus","description":"Status of the previous task that is not disabled"},{"defaultValue":"","dataType":"integer","name":"$s_Site_Hours_Day_Pre_Store.ErrorCode","description":"Error code for this task's execution"},{"defaultValue":"","dataType":"string","name":"$s_Site_Hours_Day_Pre_Store.ErrorMsg","description":"Error message for this task's execution"},{"defaultValue":"","dataType":"bigint","name":"$s_Site_Hours_Day_Pre_Store.SrcSuccessRows","description":"Rows successfully read"},{"defaultValue":"","dataType":"bigint","name":"$s_Site_Hours_Day_Pre_Store.SrcFailedRows","description":"Rows failed to read"},{"defaultValue":"","dataType":"bigint","name":"$s_Site_Hours_Day_Pre_Store.TgtSuccessRows","description":"Rows successfully loaded"},{"defaultValue":"","dataType":"bigint","name":"$s_Site_Hours_Day_Pre_Store.TgtFailedRows","description":"Rows failed to load"},{"defaultValue":"","dataType":"integer","name":"$s_Site_Hours_Day_Pre_Store.TotalTransErrors","description":"Total number of transformation errors"},{"defaultValue":"","dataType":"integer","name":"$s_Site_Hours_Day_Pre_Store.FirstErrorCode","description":"First error code"},{"defaultValue":"","dataType":"string","name":"$s_Site_Hours_Day_Pre_Store.FirstErrorMsg","description":"First error message"},{"defaultValue":"","dataType":"date/time","name":"$s_Site_Hours_Day_Pre_Vendor.StartTime","description":"The time this task started"},{"defaultValue":"","dataType":"date/time","name":"$s_Site_Hours_Day_Pre_Vendor.EndTime","description":"The time this task completed"},{"defaultValue":"","dataType":"integer","name":"$s_Site_Hours_Day_Pre_Vendor.Status","description":"Status of this task's execution"},{"defaultValue":"","dataType":"integer","name":"$s_Site_Hours_Day_Pre_Vendor.PrevTaskStatus","description":"Status of the previous task that is not disabled"},{"defaultValue":"","dataType":"integer","name":"$s_Site_Hours_Day_Pre_Vendor.ErrorCode","description":"Error code for this task's execution"},{"defaultValue":"","dataType":"string","name":"$s_Site_Hours_Day_Pre_Vendor.ErrorMsg","description":"Error message for this task's execution"},{"defaultValue":"","dataType":"bigint","name":"$s_Site_Hours_Day_Pre_Vendor.SrcSuccessRows","description":"Rows successfully read"},{"defaultValue":"","dataType":"bigint","name":"$s_Site_Hours_Day_Pre_Vendor.SrcFailedRows","description":"Rows failed to read"},{"defaultValue":"","dataType":"bigint","name":"$s_Site_Hours_Day_Pre_Vendor.TgtSuccessRows","description":"Rows successfully loaded"},{"defaultValue":"","dataType":"bigint","name":"$s_Site_Hours_Day_Pre_Vendor.TgtFailedRows","description":"Rows failed to load"},{"defaultValue":"","dataType":"integer","name":"$s_Site_Hours_Day_Pre_Vendor.TotalTransErrors","description":"Total number of transformation errors"},{"defaultValue":"","dataType":"integer","name":"$s_Site_Hours_Day_Pre_Vendor.FirstErrorCode","description":"First error code"},{"defaultValue":"","dataType":"string","name":"$s_Site_Hours_Day_Pre_Vendor.FirstErrorMsg","description":"First error message"}],"schedular":{"name":"Scheduler","description":"","type":""},"name":"wf_Site_Hours_Day","workflowType":"mainWF","id":"wf_Site_Hours_Day","version":1,"steps":[{"nextToExecute":[{"condition":"","stepId":"s_Site_Hours_Day_Pre_Store"}],"stepType":"Start","onFailure":{"FAIL_PARENT_IF_INSTANCE_FAILS":"","FAIL_PARENT_IF_INSTANCE_DID_NOT_RUN":""},"id":"Start","triggerRule":"","operator":"Start","script":""},{"nextToExecute":[{"condition":"$s_Site_Hours_Day_Pre_Store.PrevTaskStatus=Succeeded","stepId":"s_Site_Hours_Day_Pre_DC"}],"stepType":"Session","onFailure":{"FAIL_PARENT_IF_INSTANCE_FAILS":"YES","FAIL_PARENT_IF_INSTANCE_DID_NOT_RUN":"NO"},"id":"s_Site_Hours_Day_Pre_Store","triggerRule":"all_success","operator":"Session","script":"7/140/target/transformed/BA_Dimension/v1/mappings/m_Site_Hours_Day_Pre_Store.py"},{"nextToExecute":[{"condition":"","stepId":"s_Site_Hours_Day_Pre_Vendor"}],"stepType":"Session","onFailure":{"FAIL_PARENT_IF_INSTANCE_FAILS":"YES","FAIL_PARENT_IF_INSTANCE_DID_NOT_RUN":"NO"},"id":"s_Site_Hours_Day_Pre_DC","triggerRule":"all_success","operator":"Session","script":"7/140/target/transformed/BA_Dimension/v1/mappings/m_Site_Hours_Day_Pre_DC.py"},{"nextToExecute":[{"condition":"","stepId":"s_Site_Hours_Day"}],"stepType":"Session","onFailure":{"FAIL_PARENT_IF_INSTANCE_FAILS":"YES","FAIL_PARENT_IF_INSTANCE_DID_NOT_RUN":"NO"},"id":"s_Site_Hours_Day_Pre_Vendor","triggerRule":"all_success","operator":"Session","script":"7/140/target/transformed/BA_Dimension/v1/mappings/m_Site_Hours_Day_Pre_Vendor.py"},{"nextToExecute":[],"stepType":"Session","onFailure":{"FAIL_PARENT_IF_INSTANCE_FAILS":"YES","FAIL_PARENT_IF_INSTANCE_DID_NOT_RUN":"NO"},"id":"s_Site_Hours_Day","triggerRule":"all_success","operator":"Session","script":"7/140/target/transformed/BA_Dimension/v1/mappings/m_Site_Hours_Day.py"}],"notifications":null}]